{"v":5,"entries":{"configure-your-project--docs":{"id":"configure-your-project--docs","title":"Configure your project","name":"Docs","importPath":"./src/stories/Configure.mdx","storiesImports":[],"type":"docs","tags":["dev","test","unattached-mdx"]},"pages-button--primary":{"type":"story","id":"pages-button--primary","name":"Primary","title":"Pages/Button","importPath":"./src/app/pages/button/button.stories.ts","componentPath":"./src/app/pages/button/button.component.ts","tags":["dev","test"]},"pages-button--secondary":{"type":"story","id":"pages-button--secondary","name":"Secondary","title":"Pages/Button","importPath":"./src/app/pages/button/button.stories.ts","componentPath":"./src/app/pages/button/button.component.ts","tags":["dev","test"]},"pages-button--success":{"type":"story","id":"pages-button--success","name":"Success","title":"Pages/Button","importPath":"./src/app/pages/button/button.stories.ts","componentPath":"./src/app/pages/button/button.component.ts","tags":["dev","test"]},"pages-button--danger":{"type":"story","id":"pages-button--danger","name":"Danger","title":"Pages/Button","importPath":"./src/app/pages/button/button.stories.ts","componentPath":"./src/app/pages/button/button.component.ts","tags":["dev","test"]},"pages-button--random":{"type":"story","id":"pages-button--random","name":"Random","title":"Pages/Button","importPath":"./src/app/pages/button/button.stories.ts","componentPath":"./src/app/pages/button/button.component.ts","tags":["dev","test"]},"pages-input--default":{"type":"story","id":"pages-input--default","name":"Default","title":"Pages/Input","importPath":"./src/app/pages/input/input.stories.ts","componentPath":"./src/app/pages/input/input.component.ts","tags":["dev","test"]},"pages-input--filled-value":{"type":"story","id":"pages-input--filled-value","name":"Filled Value","title":"Pages/Input","importPath":"./src/app/pages/input/input.stories.ts","componentPath":"./src/app/pages/input/input.component.ts","tags":["dev","test"]},"pages-input--filled-value-disabled":{"type":"story","id":"pages-input--filled-value-disabled","name":"Filled Value Disabled","title":"Pages/Input","importPath":"./src/app/pages/input/input.stories.ts","componentPath":"./src/app/pages/input/input.component.ts","tags":["dev","test"]},"example-button--docs":{"id":"example-button--docs","title":"Example/Button","name":"Docs","importPath":"./src/stories/button.stories.ts","type":"docs","tags":["dev","test","autodocs"],"storiesImports":[]},"example-button--primary":{"type":"story","id":"example-button--primary","name":"Primary","title":"Example/Button","importPath":"./src/stories/button.stories.ts","componentPath":"./src/stories/button.component.ts","tags":["dev","test","autodocs"]},"example-button--secondary":{"type":"story","id":"example-button--secondary","name":"Secondary","title":"Example/Button","importPath":"./src/stories/button.stories.ts","componentPath":"./src/stories/button.component.ts","tags":["dev","test","autodocs"]},"example-button--large":{"type":"story","id":"example-button--large","name":"Large","title":"Example/Button","importPath":"./src/stories/button.stories.ts","componentPath":"./src/stories/button.component.ts","tags":["dev","test","autodocs"]},"example-button--small":{"type":"story","id":"example-button--small","name":"Small","title":"Example/Button","importPath":"./src/stories/button.stories.ts","componentPath":"./src/stories/button.component.ts","tags":["dev","test","autodocs"]},"example-header--docs":{"id":"example-header--docs","title":"Example/Header","name":"Docs","importPath":"./src/stories/header.stories.ts","type":"docs","tags":["dev","test","autodocs"],"storiesImports":[]},"example-header--logged-in":{"type":"story","id":"example-header--logged-in","name":"Logged In","title":"Example/Header","importPath":"./src/stories/header.stories.ts","componentPath":"./src/stories/header.component.ts","tags":["dev","test","autodocs"]},"example-header--logged-out":{"type":"story","id":"example-header--logged-out","name":"Logged Out","title":"Example/Header","importPath":"./src/stories/header.stories.ts","componentPath":"./src/stories/header.component.ts","tags":["dev","test","autodocs"]},"example-page--logged-out":{"type":"story","id":"example-page--logged-out","name":"Logged Out","title":"Example/Page","importPath":"./src/stories/page.stories.ts","componentPath":"./src/stories/page.component.ts","tags":["dev","test"]},"example-page--logged-in":{"type":"story","id":"example-page--logged-in","name":"Logged In","title":"Example/Page","importPath":"./src/stories/page.stories.ts","componentPath":"./src/stories/page.component.ts","tags":["dev","test","play-fn"]}}}